km_data_crawler/__init__.py
km_data_crawler/main.py
km_data_crawler-0.1.1.dist-info/METADATA
km_data_crawler-0.1.1.dist-info/WHEEL
km_data_crawler-0.1.1.dist-info/RECORD
